gsheetdf/__init__.py
gsheetdf/gsheetdf.py
gsheetdf-1.1.0.dist-info/METADATA
gsheetdf-1.1.0.dist-info/RECORD
gsheetdf-1.1.0.dist-info/WHEEL
gsheetdf-1.1.0.dist-info/top_level.txt
